tcev_transformation/__init__.py
tcev_transformation/convolution.py
tcev_transformation/transpose.py
tcev_transformation/ts_window.py
tcev_transformation-1.0.1.dist-info/METADATA
tcev_transformation-1.0.1.dist-info/WHEEL
tcev_transformation-1.0.1.dist-info/RECORD
