Metadata-Version: 2.1
Name: tcev-transformation
Version: 1.0.1
Summary: Library for common data transformations utilizing only the standard Python library and/or Numpy. Includes transposition, time series windowing, cross-correlation.
Author: Ernestas Vainorius
Requires-Python: >=3.10,<4.0
Classifier: Programming Language :: Python :: 3
Classifier: Programming Language :: Python :: 3.10
Classifier: Programming Language :: Python :: 3.11
Requires-Dist: numpy (>=1.24.3,<2.0.0)
Requires-Dist: pytest (>=7.3.1,<8.0.0)
